elli_api_client/CHANGELOG.md
elli_api_client/README.md
elli_api_client/__init__.py
elli_api_client/client.py
elli_api_client/config.py
elli_api_client/models.py
elli_api_client-2.0.0.dist-info/licenses/LICENSE
elli_api_client-2.0.0.dist-info/METADATA
elli_api_client-2.0.0.dist-info/WHEEL
elli_api_client-2.0.0.dist-info/top_level.txt
elli_api_client-2.0.0.dist-info/RECORD
