Metadata-Version: 2.4
Name: elli-api-client
Version: 2.0.0
Summary: Python client for Elli Charging API with OAuth2 PKCE authentication
Home-page: https://github.com/marcszy91/elli-charge-api
Author: Marc Szymkowiak
License: MIT
Project-URL: Homepage, https://github.com/marcszy91/elli-charge-api
Project-URL: Bug Tracker, https://github.com/marcszy91/elli-charge-api/issues
Project-URL: Documentation, https://github.com/marcszy91/elli-charge-api#readme
Project-URL: Source Code, https://github.com/marcszy91/elli-charge-api
Classifier: Development Status :: 3 - Alpha
Classifier: Intended Audience :: Developers
Classifier: License :: OSI Approved :: MIT License
Classifier: Operating System :: OS Independent
Classifier: Programming Language :: Python :: 3
Classifier: Programming Language :: Python :: 3.11
Classifier: Programming Language :: Python :: 3.12
Classifier: Topic :: Software Development :: Libraries :: Python Modules
Requires-Python: >=3.11
License-File: LICENSE
Requires-Dist: httpx>=0.27.0
Requires-Dist: pydantic>=2.9.0
Requires-Dist: pydantic-settings>=2.5.0
Provides-Extra: dev
Requires-Dist: pytest>=8.1.1; extra == "dev"
Requires-Dist: pytest-asyncio>=0.23.6; extra == "dev"
Requires-Dist: black>=24.3.0; extra == "dev"
Requires-Dist: isort>=5.13.2; extra == "dev"
Requires-Dist: flake8>=7.0.0; extra == "dev"
Dynamic: home-page
Dynamic: license-file
Dynamic: requires-python
